{
  "id": "3xVODHSBXWyDsgQ",
  "unique_key": "https://webscraper.io/test-sites/e-commerce/static/product/35",
  "order_no": null,
  "handled_at": "2025-04-25 16:01:40.480501+00:00",
  "request": {
    "url": "https://webscraper.io/test-sites/e-commerce/static/product/35",
    "method": "GET",
    "headers": {},
    "payload": null,
    "user_data": {
      "__crawlee": {
        "state": 5,
        "crawlDepth": 1
      },
      "label": "DETAIL"
    },
    "retry_count": 2,
    "no_retry": false,
    "loaded_url": "https://webscraper.io/test-sites/e-commerce/static/product/35",
    "handled_at": "2025-04-25 16:01:40.480501+00:00",
    "unique_key": "https://webscraper.io/test-sites/e-commerce/static/product/35",
    "id": "3xVODHSBXWyDsgQ"
  }
}